{"version":1,"resource":"vscode-remote://ssh-remote%2Biujeong/home/iujeong/Study/withpaw/pet_management.py","entries":[{"id":"S2FG.py","source":"pet_management.ipynb 이름을 pet_management.py(으)로 바꾸기","timestamp":1737204897578},{"id":"5oyP.py","timestamp":1737205315572},{"id":"kGaB.py","timestamp":1737205630379},{"id":"DntY.py","timestamp":1737205787155},{"id":"Ebpo.py","timestamp":1737206566473},{"id":"LXhP.py","timestamp":1737207023085},{"id":"PaE8.py","timestamp":1737207465030},{"id":"x2vN.py","timestamp":1737207699883},{"id":"igaM.py","timestamp":1737207762976}]}